pyusbiss-0.2.2.dist-info/DESCRIPTION.rst
pyusbiss-0.2.2.dist-info/METADATA
pyusbiss-0.2.2.dist-info/RECORD
pyusbiss-0.2.2.dist-info/WHEEL
pyusbiss-0.2.2.dist-info/metadata.json
pyusbiss-0.2.2.dist-info/top_level.txt
usbiss/__init__.py
usbiss/spi.py
usbiss/usbiss.py
