Metadata-Version: 2.0
Name: pyusbiss
Version: 0.2.2
Summary: A Python module for interfacing with USB-ISS multifunction USB Communication Module
Home-page: https://github.com/DancingQuanta/pyusbiss
Author: Andrew Tolmie
Author-email: andytheseeker@gmail.com
License: MIT license
Keywords: pyusbiss,USB-ISS,SPI,I2C,serial
Platform: UNKNOWN
Classifier: Development Status :: 2 - Pre-Alpha
Classifier: Intended Audience :: Developers
Classifier: License :: OSI Approved :: MIT License
Classifier: Natural Language :: English
Classifier: Programming Language :: Python :: 3
Classifier: Programming Language :: Python :: 3.3
Classifier: Programming Language :: Python :: 3.4
Classifier: Programming Language :: Python :: 3.5
Requires-Dist: pyserial
